pylgrim/ESPP.py
pylgrim/ESPPRC.py
pylgrim/__init__.py
pylgrim/path.py
pylgrim/tools.py
pylgrim-1.0.5.dist-info/LICENSE
pylgrim-1.0.5.dist-info/METADATA
pylgrim-1.0.5.dist-info/WHEEL
pylgrim-1.0.5.dist-info/top_level.txt
pylgrim-1.0.5.dist-info/RECORD
