Metadata-Version: 2.1
Name: pylgrim
Version: 1.0.5
Summary: Elementary shortest path problems, with or without resource constraints
Home-page: https://github.com/ToonWeyens/pylgrim
Author: Toon Weyens
Author-email: weyenst@gmail.com
License: UNKNOWN
Keywords: espp,espprc,shortest-path,graph,python
Platform: UNKNOWN
Classifier: Programming Language :: Python :: 3
Classifier: License :: OSI Approved :: GNU General Public License v3 (GPLv3)
Classifier: Operating System :: OS Independent
Requires-Dist: networkx
Requires-Dist: numpy
Requires-Dist: matplotlib (<3.3)
